adafruit_fxos8700.py
adafruit_circuitpython_fxos8700-3.0.7.dist-info/licenses/LICENSE
adafruit_circuitpython_fxos8700-3.0.7.dist-info/METADATA
adafruit_circuitpython_fxos8700-3.0.7.dist-info/WHEEL
adafruit_circuitpython_fxos8700-3.0.7.dist-info/top_level.txt
adafruit_circuitpython_fxos8700-3.0.7.dist-info/RECORD
