Metadata-Version: 2.4
Name: adafruit-circuitpython-fxos8700
Version: 3.0.7
Summary: CircuitPython library for NXP FXOS8700 accelerometer and magnetometer.
Author-email: Adafruit Industries <circuitpython@adafruit.com>
License: MIT
Project-URL: Homepage, https://github.com/adafruit/Adafruit_CircuitPython_FXOS8700
Keywords: adafruit,nxp,fxos8700,accelerometer,magnetometer,breakout,hardware,micropython,circuitpython
Classifier: Intended Audience :: Developers
Classifier: Topic :: Software Development :: Libraries
Classifier: Topic :: Software Development :: Embedded Systems
Classifier: Topic :: System :: Hardware
Classifier: License :: OSI Approved :: MIT License
Classifier: Programming Language :: Python :: 3
License-File: LICENSE
Requires-Dist: Adafruit-Blinka
Requires-Dist: adafruit-circuitpython-busdevice>=2.2.5
Provides-Extra: optional
Dynamic: license-file
